README.md
jun18th.py
setup.py
jun18th.egg-info/PKG-INFO
jun18th.egg-info/SOURCES.txt
jun18th.egg-info/dependency_links.txt
jun18th.egg-info/entry_points.txt
jun18th.egg-info/top_level.txt