Metadata-Version: 2.1
Name: jun18th
Version: 1.0.1
Summary: jun18th
Home-page: https://www.pycourses.com/double12
Author: dongweiming
Author-email: admin@pycourses.com
License: MIT
Platform: UNKNOWN
Classifier: License :: OSI Approved :: MIT License
Classifier: Programming Language :: Python
Classifier: Programming Language :: Python :: 2
Classifier: Programming Language :: Python :: 3
